Client/__init__.py
Client/client.py
Client/client/__init__.py
Client/client/add_contact.py
Client/client/core.py
Client/client/database.py
Client/client/del_contact.py
Client/client/main_window.py
Client/client/main_window_conv.py
Client/client/start_dialog.py
Client/client/transport.py
Client/common/__init__.py
Client/common/decos.py
Client/common/descryptors.py
Client/common/errors.py
Client/common/metaclasses.py
Client/common/utils.py
Client/common/variables.py
Client/logs/__init__.py
Client/logs/config_client_log.py
Client/logs/config_server_log.py
Client/unit_tests/__init__.py
message_client_test-0.0.1.dist-info/METADATA
message_client_test-0.0.1.dist-info/WHEEL
message_client_test-0.0.1.dist-info/top_level.txt
message_client_test-0.0.1.dist-info/RECORD
