Metadata-Version: 2.1
Name: message-client-test
Version: 0.0.1
Summary: message_client
Home-page: UNKNOWN
Author: gb_and_i
Author-email: vaspupiy@mail.ru
License: UNKNOWN
Platform: UNKNOWN
Requires-Dist: PyQt5
Requires-Dist: sqlalchemy
Requires-Dist: pycryptodome
Requires-Dist: pycryptodomex
